zetane/socket.cpython-39-x86_64-linux-gnu.so
zetane/numpy_utils.cpython-39-x86_64-linux-gnu.so
zetane/version.py
zetane/socket.py
zetane/__main__.py
zetane/snapshot.cpython-39-x86_64-linux-gnu.so
zetane/context.py
zetane/XAI_dashboard.cpython-39-x86_64-linux-gnu.so
zetane/snapshot.py
zetane/dashboard.cpython-39-x86_64-linux-gnu.so
zetane/inference_dashboard.cpython-39-x86_64-linux-gnu.so
zetane/ZetaneViz.cpython-39-x86_64-linux-gnu.so
zetane/XAI_dashboard.py
zetane/ZetaneViz.py
zetane/expose_node_outputs.cpython-39-x86_64-linux-gnu.so
zetane/numpy_utils.py
zetane/save.py
zetane/load.py
zetane/context.cpython-39-x86_64-linux-gnu.so
zetane/save.cpython-39-x86_64-linux-gnu.so
zetane/inference_dashboard.py
zetane/__init__.py
zetane/dashboard.py
zetane/utils.py
zetane/load.cpython-39-x86_64-linux-gnu.so
zetane/utils.cpython-39-x86_64-linux-gnu.so
zetane/analytics/zanalytics.cpython-39-x86_64-linux-gnu.so
zetane/analytics/async_buffered_consumer.cpython-39-x86_64-linux-gnu.so
zetane/analytics/mixpanel.cpython-39-x86_64-linux-gnu.so
zetane/analytics/__init__.py
zetane/analytics/mixpanel_async.cpython-39-x86_64-linux-gnu.so
zetane/render/clearuniverse.py
zetane/render/debug.cpython-39-x86_64-linux-gnu.so
zetane/render/chart3D.cpython-39-x86_64-linux-gnu.so
zetane/render/vector.py
zetane/render/vector.cpython-39-x86_64-linux-gnu.so
zetane/render/model.cpython-39-x86_64-linux-gnu.so
zetane/render/numpy.py
zetane/render/pointcloud.cpython-39-x86_64-linux-gnu.so
zetane/render/form.cpython-39-x86_64-linux-gnu.so
zetane/render/panel.cpython-39-x86_64-linux-gnu.so
zetane/render/chart3D.py
zetane/render/chartDEPRECATED.py
zetane/render/mesh.py
zetane/render/layout.cpython-39-x86_64-linux-gnu.so
zetane/render/dashboard.cpython-39-x86_64-linux-gnu.so
zetane/render/panel.py
zetane/render/zobj.cpython-39-x86_64-linux-gnu.so
zetane/render/chart.py
zetane/render/form.py
zetane/render/table.py
zetane-1.7.4.dist-info/WHEEL
zetane-1.7.4.dist-info/RECORD
zetane-1.7.4.dist-info/METADATA
zetane-1.7.4.dist-info/LICENSE.md
zetane-1.7.4.dist-info/top_level.txt
